evmospy/__init__.py
evmospy/evmosgrpc/__init__.py
evmospy/evmosgrpc/accounts.py
evmospy/evmosgrpc/broadcaster.py
evmospy/evmosgrpc/builder.py
evmospy/evmosgrpc/constants.py
evmospy/evmosgrpc/transaction.py
evmospy/evmosgrpc/utils.py
evmospy/evmosgrpc/messages/__init__.py
evmospy/evmosgrpc/messages/gov.py
evmospy/evmosgrpc/messages/irm.py
evmospy/evmosgrpc/messages/msgsend.py
evmospy/evmosgrpc/messages/staking.py
evmospy/evmosproto/__init__.py
evmospy/evmosproto/proofs_pb2.py
evmospy/evmosproto/proofs_pb2_grpc.py
evmospy/evmosproto/cosmos/__init__.py
evmospy/evmosproto/cosmos/auth/__init__.py
evmospy/evmosproto/cosmos/auth/v1beta1/__init__.py
evmospy/evmosproto/cosmos/auth/v1beta1/auth_pb2.py
evmospy/evmosproto/cosmos/auth/v1beta1/auth_pb2_grpc.py
evmospy/evmosproto/cosmos/auth/v1beta1/genesis_pb2.py
evmospy/evmosproto/cosmos/auth/v1beta1/genesis_pb2_grpc.py
evmospy/evmosproto/cosmos/auth/v1beta1/query_pb2.py
evmospy/evmosproto/cosmos/auth/v1beta1/query_pb2_grpc.py
evmospy/evmosproto/cosmos/authz/__init__.py
evmospy/evmosproto/cosmos/authz/v1beta1/__init__.py
evmospy/evmosproto/cosmos/authz/v1beta1/authz_pb2.py
evmospy/evmosproto/cosmos/authz/v1beta1/authz_pb2_grpc.py
evmospy/evmosproto/cosmos/authz/v1beta1/event_pb2.py
evmospy/evmosproto/cosmos/authz/v1beta1/event_pb2_grpc.py
evmospy/evmosproto/cosmos/authz/v1beta1/genesis_pb2.py
evmospy/evmosproto/cosmos/authz/v1beta1/genesis_pb2_grpc.py
evmospy/evmosproto/cosmos/authz/v1beta1/query_pb2.py
evmospy/evmosproto/cosmos/authz/v1beta1/query_pb2_grpc.py
evmospy/evmosproto/cosmos/authz/v1beta1/tx_pb2.py
evmospy/evmosproto/cosmos/authz/v1beta1/tx_pb2_grpc.py
evmospy/evmosproto/cosmos/bank/__init__.py
evmospy/evmosproto/cosmos/bank/v1beta1/__init__.py
evmospy/evmosproto/cosmos/bank/v1beta1/authz_pb2.py
evmospy/evmosproto/cosmos/bank/v1beta1/authz_pb2_grpc.py
evmospy/evmosproto/cosmos/bank/v1beta1/bank_pb2.py
evmospy/evmosproto/cosmos/bank/v1beta1/bank_pb2_grpc.py
evmospy/evmosproto/cosmos/bank/v1beta1/genesis_pb2.py
evmospy-1.0.2.dist-info/LICENSE
evmospy-1.0.2.dist-info/METADATA
evmospy-1.0.2.dist-info/WHEEL
evmospy-1.0.2.dist-info/top_level.txt
evmospy-1.0.2.dist-info/RECORD
